dbscan1d/__init__.py
dbscan1d/core.py
dbscan1d/version.py
dbscan1d-0.2.4.dist-info/licenses/LICENSE
dbscan1d-0.2.4.dist-info/METADATA
dbscan1d-0.2.4.dist-info/WHEEL
dbscan1d-0.2.4.dist-info/top_level.txt
dbscan1d-0.2.4.dist-info/RECORD
