Metadata-Version: 2.4
Name: dbscan1d
Version: 0.2.4
Summary: An efficient implementation of the DBSCAN algorithm for 1D arrays.
Author-email: Derrick Chambers <chambers.ja.derrick@gmail.com>
License:                    GNU LESSER GENERAL PUBLIC LICENSE
Project-URL: Bug Tracker, https://github.com/d-chambers/dbscan1d/issues
Project-URL: Documentation, https://github.com/d-chambers/dbscan1d
Project-URL: Homepage, https://github.com/d-chambers/dbscan1d
Keywords: geophysics,distributed-acoustic-sensing
Classifier: Development Status :: 4 - Beta
Classifier: License :: OSI Approved :: GNU Lesser General Public License v3 or later (LGPLv3+)
Classifier: Programming Language :: Python :: 3.9
Classifier: Programming Language :: Python :: 3.10
Classifier: Programming Language :: Python :: 3.11
Classifier: Programming Language :: Python :: 3.12
Classifier: Programming Language :: Python :: 3.13
Classifier: Topic :: Scientific/Engineering
Requires-Python: >=3.9
License-File: LICENSE
Requires-Dist: numpy>=1.25.0
Provides-Extra: test
Requires-Dist: pytest; extra == "test"
Requires-Dist: pytest-cov; extra == "test"
Requires-Dist: scikit-learn; extra == "test"
Provides-Extra: dev
Requires-Dist: dbscan1d[test]; extra == "dev"
Dynamic: license-file
